Metadata-Version: 2.1
Name: Sparragon
Version: 0.0.2
Summary: Python library to interact with Galaxy Life 
Home-page: http://github.com/twoolie/NBT
Author: Folfy Blue
License:                     GNU GENERAL PUBLIC LICENSE
License-File: LICENSE
